qtextras/__init__.py
qtextras/_funcparse.py
qtextras/constants.py
qtextras/fns.py
qtextras/shims.py
qtextras/typeoverloads.py
qtextras/examples/__init__.py
qtextras/examples/parameditor.py
qtextras/misc/__init__.py
qtextras/misc/actionstack.py
qtextras/misc/composition.py
qtextras/misc/logger.py
qtextras/misc/models.py
qtextras/params/__init__.py
qtextras/params/editor.py
qtextras/params/optionsdict.py
qtextras/params/pgregistered.py
qtextras/widgets/__init__.py
qtextras/widgets/buttoncollection.py
qtextras/widgets/console.py
qtextras/widgets/easywidget.py
qtextras/widgets/imageviewer.py
qtextras/widgets/lineeditor.py
qtextras/widgets/loghandlers.py
qtextras-0.6.8.dist-info/METADATA
qtextras-0.6.8.dist-info/WHEEL
qtextras-0.6.8.dist-info/RECORD
