Metadata-Version: 2.3
Name: qtextras
Version: 0.6.8
Summary: High-level widgets and features for scientific Qt GUI development
Author-email: Nathan Jessurun <ntjessu@gmail.com>
License: MIT
Classifier: Development Status :: 3 - Alpha
Classifier: Intended Audience :: Developers
Classifier: License :: OSI Approved :: MIT License
Classifier: Programming Language :: Python :: 3
Classifier: Topic :: Software Development :: Build Tools
Requires-Python: >=3.8
Requires-Dist: numpy>=1.0
Requires-Dist: pyqtgraph>=0.13.1
Requires-Dist: ruamel-yaml>=0.17.0
Provides-Extra: full
Requires-Dist: pandas>=1.4.0; extra == 'full'
Requires-Dist: pyside6>=6.2.0; extra == 'full'
